decOM/__init__.py
decOM/__main__.py
decOM/__version__.py
decOM/CV/__init__.py
decOM/CV/__main__.py
decOM/LOO/__init__.py
decOM/LOO/__main__.py
decOM/MST/__init__.py
decOM/MST/__main__.py
decOM/aOralOut/__init__.py
decOM/aOralOut/__main__.py
decOM/data/D3.fasta
decOM/data/__init__.py
decOM/data/aOralOut_kmtricks.fof
decOM/data/aOralOut_metadata.csv
decOM/data/kmtricks.fof
decOM/data/metadata.csv
decOM/data/metadata.tsv
decOM/data/metadata_sinks_0_fold.csv
decOM/data/metadata_sinks_1_fold.csv
decOM/data/metadata_sinks_2_fold.csv
decOM/data/metadata_sinks_3_fold.csv
decOM/data/metadata_sinks_4_fold.csv
decOM/data/metadata_sources_0_fold.csv
decOM/data/metadata_sources_1_fold.csv
decOM/data/metadata_sources_2_fold.csv
decOM/data/metadata_sources_3_fold.csv
decOM/data/metadata_sources_4_fold.csv
decOM/format/__init__.py
decOM/format/__main__.py
decOM/modules/__init__.py
decOM/modules/sink.py
decOM/modules/utils.py
test/__init__.py
test/pytest_test.py
decOM-0.0.32.dist-info/LICENSE
decOM-0.0.32.dist-info/METADATA
decOM-0.0.32.dist-info/WHEEL
decOM-0.0.32.dist-info/entry_points.txt
decOM-0.0.32.dist-info/top_level.txt
decOM-0.0.32.dist-info/RECORD
