Metadata-Version: 2.1
Name: decOM
Version: 0.0.32
Summary: decOM: Similarity-based microbial source tracking for contamination assessment of ancient oral samples using k-mer-based methods
Home-page: https://github.com/CamilaDuitama/decOM
Author: Camila Duitama González
Author-email: cduitama@pasteur.fr
Project-URL: Bug Tracker, https://github.com/CamilaDuitama/decOM/issues
Classifier: Programming Language :: Python :: 3
Classifier: License :: OSI Approved :: MIT License
Classifier: Operating System :: OS Independent
Requires-Python: >=3.6
License-File: LICENSE
Requires-Dist: plotly (>=5.5.0)
Requires-Dist: importlib-resources (>=5.4.0)
Requires-Dist: dask (>=2021.12.0)
Requires-Dist: numpy
Requires-Dist: kaleido
Requires-Dist: colorama
Requires-Dist: pandas
